4/project_4/project_4.srcs/sources_1/new/machine.v
`timescale 1ns / 1ps

module machine(
    input clk,
    input rstn,
    input [1:0] coin,
    output reg sell,
    output reg change
);

    // 状态定义
    parameter IDLE  = 3'b000;
    parameter GET05 = 3'b001;
    parameter GET10 = 3'b010;
    parameter GET15 = 3'b011;
    parameter SOLD  = 3'b100;
    parameter CHANGE = 3'b101;
    
    reg [2:0] current_state;
    reg [2:0] next_state;
    
    // 第一个always块：状态寄存器（时序逻辑）
    always @(posedge clk or negedge rstn) begin
        if (!rstn)
            current_state <= IDLE;
        else
            current_state <= next_state;
    end
    
    // 第二个always块：状态转移逻辑（组合逻辑）
    always @(*) begin
        case (current_state)
            IDLE: begin
                if (coin == 2'b01)          // 投入0.5元
                    next_state = GET05;
                else if (coin == 2'b10)     // 投入1元
                    next_state = GET10;
                else
                    next_state = IDLE;
            end
            
            GET05: begin
                if (coin == 2'b01)          // 再投0.5元
                    next_state = GET10;
                else if (coin == 2'b10)     // 再投1元
                    next_state = GET15;
                else
                    next_state = GET05;
            end
            
            GET10: begin
                if (coin == 2'b01)          // 再投0.5元
                    next_state = GET15;
                else if (coin == 2'b10)     // 再投1元
                    next_state = SOLD;
                else
                    next_state = GET10;
            end
            
            GET15: begin
                if (coin == 2'b01)          // 再投0.5元
                    next_state = SOLD;
                else if (coin == 2'b10)     // 再投1元
                    next_state = CHANGE;
                else
                    next_state = GET15;
            end
            
            SOLD: begin
                next_state = IDLE;
            end
            
            CHANGE: begin
                next_state = IDLE;
            end
            
            default: next_state = IDLE;
        endcase
    end
    
    // 第三个always块：输出逻辑（时序逻辑）
    always @(posedge clk or negedge rstn) begin
        if (!rstn) begin
            sell <= 0;
            change <= 0;
        end else begin
            // 默认输出
            sell <= 0;
            change <= 0;
            
            // 根据下一个状态设置输出
            case (next_state)
                SOLD: begin
                    sell <= 1;
                    change <= 0;
                end
                
                CHANGE: begin
                    sell <= 1;
                    change <= 1;
                end
            endcase
        end
    end

endmodule

4/project_4/project_4.srcs/sim_1/new/test.v
`timescale 1ns / 1ps

module test;
    reg clk;
    reg rstn;
    reg [1:0] coin;
    wire sell;
    wire change;
    
    // 实例化被测模块
    machine uut (
        .clk(clk),
        .rstn(rstn),
        .coin(coin),
        .sell(sell),
        .change(change)
    );
    
    // 时钟生成
    always #5 clk = ~clk;
    
    // 状态名称定义，用于更好的显示
    reg [39:0] state_name;
    always @(uut.current_state) begin
        case (uut.current_state)
            3'b000: state_name = "IDLE";
            3'b001: state_name = "GET05";
            3'b010: state_name = "GET10";
            3'b011: state_name = "GET15";
            3'b100: state_name = "SOLD";
            3'b101: state_name = "CHANGE";
            default: state_name = "UNKNOWN";
        endcase
    end
    
    initial begin
        // 初始化信号
        clk = 0;
        rstn = 0;
        coin = 2'b00;
        
        // 生成VCD文件用于详细分析
        $dumpfile("wave.vcd");
        $dumpvars(0, test);
        
        // 复位
        #20;
        rstn = 1;
        
        $display("=== 测试开始 ===");
        $display("Time\tState\t\tCoin\tSell\tChange");
        $display("----\t-----\t\t----\t----\t------");
        
        // 测试用例1: 投入4个0.5元硬币
        $display("\n测试1: 4个0.5元硬币");
        #10; coin = 2'b01;  // 投0.5元
        #10; coin = 2'b00;
        #10; coin = 2'b01;  // 再投0.5元
        #10; coin = 2'b00;
        #10; coin = 2'b01;  // 再投0.5元
        #10; coin = 2'b00;
        #10; coin = 2'b01;  // 再投0.5元
        #10; coin = 2'b00;
        
        #30; // 等待出货完成
        
        // 测试用例2: 投入2个1元硬币
        $display("\n测试2: 2个1元硬币");
        #10; coin = 2'b10;  // 投1元
        #10; coin = 2'b00;
        #10; coin = 2'b10;  // 再投1元
        #10; coin = 2'b00;
        
        #30; // 等待出货完成
        
        // 测试用例3: 投入1元+0.5元+0.5元
        $display("\n测试3: 1元+0.5元+0.5元");
        #10; coin = 2'b10;  // 投1元
        #10; coin = 2'b00;
        #10; coin = 2'b01;  // 投0.5元
        #10; coin = 2'b00;
        #10; coin = 2'b01;  // 再投0.5元
        #10; coin = 2'b00;
        
        #30; // 等待出货完成
        
        // 测试用例4: 投入1元+1元（需要找零）
        $display("\n测试4: 1元+1元（找零）");
        #10; coin = 2'b10;  // 投1元
        #10; coin = 2'b00;
        #10; coin = 2'b10;  // 再投1元
        #10; coin = 2'b00;
        
        #30; // 等待出货和找零完成
        
        $display("\n=== 测试结束 ===");
        $finish;
    end
    
    // 在每个时钟上升沿显示状态信息
    always @(posedge clk) begin
        $display("%0t\t%s\t%b\t%b\t%b", 
                 $time, state_name, coin, sell, change);
    end

endmodule

4/project_4/project_4.sim/sim_1/behav/xsim/wave.vcd
$date
   Thu Nov  6 23:39:44 2025
$end

$version
  2023.2
  $dumpfile ("wave.vcd") 
$end

$timescale
  1ps
$end

$scope module test $end
$var reg 1 ! clk $end
$var reg 1 " rstn $end
$var reg 2 # coin [1:0] $end
$var wire 1 $ sell $end
$var wire 1 % change $end
$var reg 40 & state_name [39:0] $end
$scope module uut $end
$var wire 1 ' clk $end
$var wire 1 ( rstn $end
$var wire 2 ) coin [1:0] $end
$var reg 1 * sell $end
$var reg 1 + change $end
$var reg 3 , current_state [2:0] $end
$var reg 3 - next_state [2:0] $end
$upscope $end
$upscope $end
$enddefinitions $end

#0
$dumpvars
0!
0"
b0 #
0$
0%
b1001001010001000100110001000101 &
0'
0(
b0 )
0*
0+
b0 ,
b0 -
$end

#5000
1!
1'

#10000
0!
0'

#15000
1!
1'

#20000
0!
1"
0'
1(

#25000
1!
1'

#30000
0!
b1 #
0'
b1 )
b1 -

#35000
1!
b100011101000101010101000011000000110101 &
1'
b1 ,
b10 -

#40000
0!
b0 #
0'
b0 )
b1 -

#45000
1!
1'

#50000
0!
b1 #
0'
b1 )
b10 -

#55000
1!
b100011101000101010101000011000100110000 &
1'
b10 ,
b11 -

#60000
0!
b0 #
0'
b0 )
b10 -

#65000
1!
1'

#70000
0!
b1 #
0'
b1 )
b11 -

#75000
1!
b100011101000101010101000011000100110101 &
1'
b11 ,
b100 -

#80000
0!
b0 #
0'
b0 )
b11 -

#85000
1!
1'

#90000
0!
b1 #
0'
b1 )
b100 -

#95000
1!
1$
b1010011010011110100110001000100 &
1'
1*
b100 ,
b0 -

#100000
0!
b0 #
0'
b0 )

#105000
1!
0$
b1001001010001000100110001000101 &
1'
0*
b0 ,

#110000
0!
0'

#115000
1!
1'

#120000
0!
0'

#125000
1!
1'

#130000
0!
0'

#135000
1!
1'

#140000
0!
b10 #
0'
b10 )
b10 -

#145000
1!
b100011101000101010101000011000100110000 &
1'
b10 ,
b100 -

#150000
0!
b0 #
0'
b0 )
b10 -

#155000
1!
1'

#160000
0!
b10 #
0'
b10 )
b100 -

#165000
1!
1$
b1010011010011110100110001000100 &
1'
1*
b100 ,
b0 -

#170000
0!
b0 #
0'
b0 )

#175000
1!
0$
b1001001010001000100110001000101 &
1'
0*
b0 ,

#180000
0!
0'

#185000
1!
1'

#190000
0!
0'

#195000
1!
1'

#200000
0!
0'

#205000
1!
1'

#210000
0!
b10 #
0'
b10 )
b10 -

#215000
1!
b100011101000101010101000011000100110000 &
1'
b10 ,
b100 -

#220000
0!
b0 #
0'
b0 )
b10 -

#225000
1!
1'

#230000
0!
b1 #
0'
b1 )
b11 -

#235000
1!
b100011101000101010101000011000100110101 &
1'
b11 ,
b100 -

#240000
0!
b0 #
0'
b0 )
b11 -

#245000
1!
1'

#250000
0!
b1 #
0'
b1 )
b100 -

#255000
1!
1$
b1010011010011110100110001000100 &
1'
1*
b100 ,
b0 -

#260000
0!
b0 #
0'
b0 )

#265000
1!
0$
b1001001010001000100110001000101 &
1'
0*
b0 ,

#270000
0!
0'

#275000
1!
1'

#280000
0!
0'

#285000
1!
1'

#290000
0!
0'

#295000
1!
1'

#300000
0!
b10 #
0'
b10 )
b10 -

#305000
1!
b100011101000101010101000011000100110000 &
1'
b10 ,
b100 -

#310000
0!
b0 #
0'
b0 )
b10 -

#315000
1!
1'

#320000
0!
b10 #
0'
b10 )
b100 -

#325000
1!
1$
b1010011010011110100110001000100 &
1'
1*
b100 ,
b0 -

#330000
0!
b0 #
0'
b0 )

#335000
1!
0$
b1001001010001000100110001000101 &
1'
0*
b0 ,

