4/4.srcs/sources_1/new/machine.v
`timescale 1ns / 1ps

module machine(
    input clk,
    input rstn,
    input [1:0] coin,
    output reg sell,
    output reg change
);

// 状态定义
// S0: IDLE    - 初始状态，0元
// S1: GET05   - 已投0.5元
// S2: GET10   - 已投1元  
// S3: GET15   - 已投1.5元

parameter S0 = 2'b00;  // IDLE
parameter S1 = 2'b01;  // GET05
parameter S2 = 2'b10;  // GET10
parameter S3 = 2'b11;  // GET15

reg [1:0] current_state;
reg [1:0] next_state;

// 第一段：状态寄存器（时序逻辑）
always @(posedge clk or negedge rstn) begin
    if (!rstn) begin
        current_state <= S0;
    end else begin
        current_state <= next_state;
    end
end

// 第二段：状态转移逻辑（组合逻辑）
always @(*) begin
    case (current_state)
        S0: begin  // IDLE
            if (coin == 2'b01) begin        // 投入0.5元
                next_state = S1;
            end else if (coin == 2'b10) begin // 投入1元
                next_state = S2;
            end else begin
                next_state = S0;
            end
        end
        
        S1: begin  // GET05
            if (coin == 2'b01) begin        // 再投入0.5元
                next_state = S2;
            end else if (coin == 2'b10) begin // 再投入1元
                next_state = S3;
            end else begin
                next_state = S1;
            end
        end
        
        S2: begin  // GET10
            if (coin == 2'b01) begin        // 再投入0.5元
                next_state = S3;
            end else if (coin == 2'b10) begin // 再投入1元（达到2元）
                next_state = S0;
            end else begin
                next_state = S2;
            end
        end
        
        S3: begin  // GET15
            if (coin == 2'b01) begin        // 再投入0.5元（达到2元）
                next_state = S0;
            end else if (coin == 2'b10) begin // 再投入1元（达到2.5元）
                next_state = S0;
            end else begin
                next_state = S3;
            end
        end
        
        default: next_state = S0;
    endcase
end

// 第三段：输出逻辑（时序逻辑）
always @(posedge clk or negedge rstn) begin
    if (!rstn) begin
        sell <= 1'b0;
        change <= 1'b0;
    end else begin
        // 默认输出
        sell <= 1'b0;
        change <= 1'b0;
        
        case (current_state)
            S2: begin  // GET10
                if (coin == 2'b10) begin    // 投入1元达到2元，出货不找零
                    sell <= 1'b1;
                    change <= 1'b0;
                end
            end
            
            S3: begin  // GET15
                if (coin == 2'b01) begin    // 投入0.5元达到2元，出货不找零
                    sell <= 1'b1;
                    change <= 1'b0;
                end else if (coin == 2'b10) begin // 投入1元达到2.5元，出货并找零
                    sell <= 1'b1;
                    change <= 1'b1;
                end
            end
        endcase
    end
end

endmodule

4/4.srcs/sim_1/new/test.v
`timescale 1ns / 1ps

module test;
    // 输入信号
    reg clk;
    reg rstn;
    reg [1:0] coin;
    
    // 输出信号
    wire sell;
    wire change;
    
    // 状态信号（为了观察内部状态）
    wire [1:0] current_state;
    
    // 实例化被测模块
    machine uut (
        .clk(clk),
        .rstn(rstn),
        .coin(coin),
        .sell(sell),
        .change(change)
    );
    
    // 为了观察内部状态，我们需要通过层次化引用
    assign current_state = uut.current_state;
    
    // 状态名称定义，使用数字表示
    reg [7:0] state_name;
    always @(*) begin
        case (current_state)
            2'b00: state_name = "S0";  // IDLE
            2'b01: state_name = "S1";  // GET05
            2'b10: state_name = "S2";  // GET10
            2'b11: state_name = "S3";  // GET15
            default: state_name = "ERR";
        endcase
    end
    
    // 时钟生成 - 周期20ns
    initial begin
        clk = 0;
        forever #10 clk = ~clk;
    end
    
    // 测试过程
    initial begin
        // 初始化信号
        rstn = 1;
        coin = 2'b00;
        
        // 等待一个时钟周期
        #15;
        
        // 打印表头
        $display("Time\tRstn\tCoin\tSell\tChange\tState");
        $display("----------------------------------------");
        
        #5 display_line();
        
        // === 测试1: 异步复位 ===
        $display("\n=== 测试1: 异步复位 ===");
        rstn = 0;  // 复位有效
        #20 display_line();
        
        rstn = 1;  // 复位解除
        #20 display_line();
        
        // === 测试2: 投入0.5元 ===
        $display("\n=== 测试2: 投入0.5元 ===");
        display_line();
        coin = 2'b01;  // 投入0.5元
        #20 display_line();
        
        // === 测试3: 再投入0.5元 ===
        $display("\n=== 测试3: 再投入0.5元 ===");
        coin = 2'b00;
        #20 display_line();
        coin = 2'b01;  // 再投入0.5元
        #20 display_line();
        
        // === 测试4: 投入1元（达到2元，出货不找零）===
        $display("\n=== 测试4: 投入1元（达到2元，出货不找零）===");
        coin = 2'b00;
        #20 display_line();
        coin = 2'b10;  // 投入1元
        #20 display_line();
        
        // === 测试5: 回到初始状态 ===
        $display("\n=== 测试5: 回到初始状态 ===");
        coin = 2'b00;
        #20 display_line();
        
        // === 测试6: 投入1元 ===
        $display("\n=== 测试6: 投入1元 ===");
        coin = 2'b10;  // 投入1元
        #20 display_line();
        
        // === 测试7: 再投入0.5元 ===
        $display("\n=== 测试7: 再投入0.5元 ===");
        coin = 2'b00;
        #20 display_line();
        coin = 2'b01;  // 投入0.5元
        #20 display_line();
        
        // === 测试8: 再投入1元（达到2.5元，出货并找零）===
        $display("\n=== 测试8: 再投入1元（达到2.5元，出货并找零）===");
        coin = 2'b00;
        #20 display_line();
        coin = 2'b10;  // 投入1元
        #20 display_line();
        
        // === 测试9: 回到初始状态 ===
        $display("\n=== 测试9: 回到初始状态 ===");
        coin = 2'b00;
        #20 display_line();
        
        // === 测试10: 异常输入测试 ===
        $display("\n=== 测试10: 异常输入测试（coin=11）===");
        coin = 2'b11;  // 异常输入
        #20 display_line();
        
        // === 仿真完成 ===
        $display("\n=== 仿真完成 ===");
        #100 $finish;
    end
    
    // 显示一行数据的任务
    task display_line;
        begin
            $display("%0d\t%0d\t%b\t%0d\t%0d\t%s", 
                    $time, rstn, coin, sell, change, state_name);
        end
    endtask
    
    // 波形保存
    initial begin
        $dumpfile("machine_wave.vcd");
        $dumpvars(0, test);
    end

endmodule

4/4.sim/sim_1/behav/xsim/machine_wave.vcd
$date
   Sat Nov 15 12:53:42 2025
$end

$version
  2023.2
  $dumpfile ("machine_wave.vcd") 
$end

$timescale
  1ps
$end

$scope module test $end
$var reg 1 ! clk $end
$var reg 1 " rstn $end
$var reg 2 # coin [1:0] $end
$var wire 1 $ sell $end
$var wire 1 % change $end
$var wire 2 & current_state [1:0] $end
$var reg 8 ' state_name [7:0] $end
$scope module uut $end
$var wire 1 ( clk $end
$var wire 1 ) rstn $end
$var wire 2 * coin [1:0] $end
$var reg 1 + sell $end
$var reg 1 , change $end
$var reg 2 - current_state [1:0] $end
$var reg 2 . next_state [1:0] $end
$upscope $end
$scope task display_line $end
$upscope $end
$upscope $end
$enddefinitions $end

#0
$dumpvars
0!
1"
b0 #
x$
x%
bx &
bx '
0(
1)
b0 *
x+
x,
bx -
b0 .
$end

#10000
1!
0$
0%
b0 &
b110000 '
1(
0+
0,
b0 -

#20000
0!
0"
0(
0)

#30000
1!
1(

#40000
0!
1"
0(
1)

#50000
1!
1(

#60000
0!
b1 #
0(
b1 *
b1 .

#70000
1!
b1 &
b110001 '
1(
b1 -
b10 .

#80000
0!
b0 #
0(
b0 *
b1 .

#90000
1!
1(

#100000
0!
b1 #
0(
b1 *
b10 .

#110000
1!
b10 &
b110010 '
1(
b10 -
b11 .

#120000
0!
b0 #
0(
b0 *
b10 .

#130000
1!
1(

#140000
0!
b10 #
0(
b10 *
b0 .

#150000
1!
1$
b0 &
b110000 '
1(
1+
b0 -
b10 .

#160000
0!
b0 #
0(
b0 *
b0 .

#170000
1!
0$
1(
0+

#180000
0!
b10 #
0(
b10 *
b10 .

#190000
1!
b10 &
b110010 '
1(
b10 -
b0 .

#200000
0!
b0 #
0(
b0 *
b10 .

#210000
1!
1(

#220000
0!
b1 #
0(
b1 *
b11 .

#230000
1!
b11 &
b110011 '
1(
b11 -
b0 .

#240000
0!
b0 #
0(
b0 *
b11 .

#250000
1!
1(

#260000
0!
b10 #
0(
b10 *
b0 .

#270000
1!
1$
1%
b0 &
b110000 '
1(
1+
1,
b0 -
b10 .

#280000
0!
b0 #
0(
b0 *
b0 .

#290000
1!
0$
0%
1(
0+
0,

#300000
0!
b11 #
0(
b11 *

